{"totalRecords": 3815858181, "month": [236158833, 206724190, 252010427, 356062807, 470039449, 366976120, 347022408, 318359191, 293221996, 271189351, 231435538, 198251974], "topSpeciesGlobal": [{"speciesKey": 9761484, "count": 33148366}, {"speciesKey": 2495347, "count": 29408502}, {"speciesKey": 9510564, "count": 29382955}, {"speciesKey": 2482507, "count": 29068014}, {"speciesKey": 9809229, "count": 28247146}, {"speciesKey": 2490384, "count": 27182953}, {"speciesKey": 5231190, "count": 25763934}, {"speciesKey": 5232437, "count": 25728609}, {"speciesKey": 2482593, "count": 24079901}, {"speciesKey": 2492196, "count": 22461298}, {"speciesKey": 9409198, "count": 21106058}, {"speciesKey": 5231640, "count": 20290022}, {"speciesKey": 8323485, "count": 19207348}, {"speciesKey": 9149595, "count": 19062013}, {"speciesKey": 2487805, "count": 18774074}, {"speciesKey": 2481930, "count": 17626120}, {"speciesKey": 9515886, "count": 17355306}, {"speciesKey": 2495414, "count": 15517862}, {"speciesKey": 2478106, "count": 15438106}, {"speciesKey": 2478259, "count": 15021320}, {"speciesKey": 9362842, "count": 14857597}, {"speciesKey": 2484892, "count": 14323160}, {"speciesKey": 9630752, "count": 14173867}, {"speciesKey": 9705453, "count": 13895370}, {"speciesKey": 2490719, "count": 13329051}, {"speciesKey": 2487887, "count": 13287918}, {"speciesKey": 9752617, "count": 12958693}, {"speciesKey": 2493801, "count": 12909481}, {"speciesKey": 2480542, "count": 12448409}, {"speciesKey": 7341805, "count": 12368158}, {"speciesKey": 2484155, "count": 12355143}, {"speciesKey": 2482492, "count": 12270048}, {"speciesKey": 5231677, "count": 11829608}, {"speciesKey": 2481134, "count": 11221492}, {"speciesKey": 2487879, "count": 11082294}, {"speciesKey": 2492462, "count": 10814993}, {"speciesKey": 2481875, "count": 10539734}, {"speciesKey": 2494422, "count": 10215199}, {"speciesKey": 2480320, "count": 9882949}, {"speciesKey": 5231140, "count": 9644389}, {"speciesKey": 2495696, "count": 9589332}, {"speciesKey": 2494936, "count": 9409467}, {"speciesKey": 2495455, "count": 9274737}, {"speciesKey": 2492109, "count": 8994014}, {"speciesKey": 2487844, "count": 8638127}, {"speciesKey": 2489670, "count": 8535212}, {"speciesKey": 2484391, "count": 8430178}, {"speciesKey": 2489181, "count": 8334919}, {"speciesKey": 5229490, "count": 8089745}, {"speciesKey": 2490941, "count": 8077841}, {"speciesKey": 2480726, "count": 7874776}, {"speciesKey": 2480446, "count": 7806666}, {"speciesKey": 9797180, "count": 7769485}, {"speciesKey": 8214667, "count": 7769116}, {"speciesKey": 9192501, "count": 7539471}, {"speciesKey": 2484597, "count": 7514876}, {"speciesKey": 2480537, "count": 7491103}, {"speciesKey": 2483606, "count": 7253375}, {"speciesKey": 2484609, "count": 7250893}, {"speciesKey": 2481139, "count": 7071782}, {"speciesKey": 7341834, "count": 7064632}, {"speciesKey": 2475472, "count": 7044991}, {"speciesKey": 2493091, "count": 7029463}, {"speciesKey": 9362027, "count": 6941010}, {"speciesKey": 2481174, "count": 6904021}, {"speciesKey": 4848480, "count": 6897325}, {"speciesKey": 9687165, "count": 6827101}, {"speciesKey": 6065824, "count": 6782155}, {"speciesKey": 2481890, "count": 6715484}, {"speciesKey": 5231132, "count": 6700124}, {"speciesKey": 2498343, "count": 6666738}, {"speciesKey": 5231459, "count": 6613659}, {"speciesKey": 5845582, "count": 6610639}, {"speciesKey": 2498387, "count": 6507768}, {"speciesKey": 8332393, "count": 6494999}, {"speciesKey": 2481942, "count": 6461683}, {"speciesKey": 2494686, "count": 6381869}, {"speciesKey": 2492956, "count": 6359733}, {"speciesKey": 2474393, "count": 6106114}, {"speciesKey": 5228199, "count": 6058466}, {"speciesKey": 2498326, "count": 5960295}, {"speciesKey": 9685907, "count": 5950954}, {"speciesKey": 2487430, "count": 5919817}, {"speciesKey": 2474377, "count": 5890635}, {"speciesKey": 5231438, "count": 5835367}, {"speciesKey": 2484879, "count": 5799598}, {"speciesKey": 9616058, "count": 5723346}, {"speciesKey": 9537647, "count": 5683016}, {"speciesKey": 9409796, "count": 5670406}, {"speciesKey": 2487596, "count": 5514673}, {"speciesKey": 2491205, "count": 5399391}, {"speciesKey": 5228824, "count": 5374416}, {"speciesKey": 2477968, "count": 5326128}, {"speciesKey": 2498329, "count": 5200974}, {"speciesKey": 2482077, "count": 5146120}, {"speciesKey": 2480487, "count": 5098663}, {"speciesKey": 2493052, "count": 5097472}, {"speciesKey": 2480529, "count": 5068547}, {"speciesKey": 2481172, "count": 5042015}, {"speciesKey": 2498036, "count": 4835835}, {"speciesKey": 9709230, "count": 4819094}, {"speciesKey": 2476674, "count": 4789370}, {"speciesKey": 2480873, "count": 4751775}, {"speciesKey": 6100954, "count": 4733441}, {"speciesKey": 5228514, "count": 4595762}, {"speciesKey": 7901064, "count": 4535455}, {"speciesKey": 2480242, "count": 4430536}, {"speciesKey": 2484340, "count": 4295677}, {"speciesKey": 5135513, "count": 4290570}, {"speciesKey": 5231198, "count": 4284526}, {"speciesKey": 5229493, "count": 4272183}, {"speciesKey": 2482515, "count": 4257442}, {"speciesKey": 5231647, "count": 4254118}, {"speciesKey": 2498112, "count": 4205939}, {"speciesKey": 5231142, "count": 4170124}, {"speciesKey": 5229688, "count": 4132880}, {"speciesKey": 2489985, "count": 4109013}, {"speciesKey": 2490327, "count": 3988919}, {"speciesKey": 2484596, "count": 3970528}, {"speciesKey": 2498375, "count": 3928846}, {"speciesKey": 2498261, "count": 3928840}, {"speciesKey": 5231763, "count": 3903088}, {"speciesKey": 4409023, "count": 3893204}, {"speciesKey": 7788295, "count": 3867244}, {"speciesKey": 2480876, "count": 3842252}, {"speciesKey": 5229734, "count": 3822550}, {"speciesKey": 9476062, "count": 3790788}, {"speciesKey": 2483612, "count": 3768895}, {"speciesKey": 2484591, "count": 3756313}, {"speciesKey": 2498155, "count": 3743812}, {"speciesKey": 8215487, "count": 3734165}, {"speciesKey": 2483597, "count": 3723783}, {"speciesKey": 2481798, "count": 3704565}, {"speciesKey": 2484916, "count": 3702737}, {"speciesKey": 2480830, "count": 3693856}, {"speciesKey": 8077224, "count": 3673461}, {"speciesKey": 2482054, "count": 3638508}, {"speciesKey": 5231635, "count": 3631675}, {"speciesKey": 9422220, "count": 3622173}, {"speciesKey": 9479809, "count": 3620328}, {"speciesKey": 2491557, "count": 3593094}, {"speciesKey": 1920496, "count": 3592111}, {"speciesKey": 2489005, "count": 3571480}, {"speciesKey": 2498264, "count": 3567825}, {"speciesKey": 2487446, "count": 3563031}, {"speciesKey": 2495370, "count": 3524558}, {"speciesKey": 2489613, "count": 3473886}, {"speciesKey": 2482481, "count": 3456325}, {"speciesKey": 2490810, "count": 3446609}, {"speciesKey": 2491534, "count": 3415500}, {"speciesKey": 2481759, "count": 3402392}, {"speciesKey": 9752149, "count": 3399605}, {"speciesKey": 8049830, "count": 3386091}, {"speciesKey": 9539567, "count": 3371417}, {"speciesKey": 2493843, "count": 3366940}, {"speciesKey": 7982160, "count": 3359103}, {"speciesKey": 2490266, "count": 3350792}, {"speciesKey": 2492235, "count": 3338892}, {"speciesKey": 2498408, "count": 3336992}, {"speciesKey": 2481720, "count": 3334597}, {"speciesKey": 2480482, "count": 3318150}, {"speciesKey": 5231630, "count": 3312970}, {"speciesKey": 2495000, "count": 3255499}, {"speciesKey": 2489202, "count": 3239576}, {"speciesKey": 2481962, "count": 3221041}, {"speciesKey": 6065844, "count": 3220129}, {"speciesKey": 5218465, "count": 3214308}, {"speciesKey": 9581438, "count": 3210434}, {"speciesKey": 6092830, "count": 3157072}, {"speciesKey": 2480863, "count": 3139186}, {"speciesKey": 2482048, "count": 3071948}, {"speciesKey": 9367409, "count": 3028034}, {"speciesKey": 6093345, "count": 3024568}, {"speciesKey": 2498305, "count": 3019367}, {"speciesKey": 2490737, "count": 3017636}, {"speciesKey": 5228676, "count": 3015571}, {"speciesKey": 8104397, "count": 3004807}, {"speciesKey": 1898286, "count": 3000767}, {"speciesKey": 2492096, "count": 3000178}, {"speciesKey": 8169649, "count": 2989741}, {"speciesKey": 9581157, "count": 2978027}, {"speciesKey": 4535827, "count": 2967907}, {"speciesKey": 7341816, "count": 2962878}, {"speciesKey": 2494543, "count": 2948971}, {"speciesKey": 2489450, "count": 2938863}, {"speciesKey": 2480637, "count": 2932168}, {"speciesKey": 2493118, "count": 2926434}, {"speciesKey": 7804446, "count": 2925728}, {"speciesKey": 2481047, "count": 2924476}, {"speciesKey": 2482414, "count": 2920268}, {"speciesKey": 8000602, "count": 2912199}, {"speciesKey": 5229158, "count": 2909007}, {"speciesKey": 1920494, "count": 2884103}, {"speciesKey": 7341822, "count": 2865334}, {"speciesKey": 9606290, "count": 2830833}, {"speciesKey": 2481714, "count": 2826437}, {"speciesKey": 2481745, "count": 2825900}, {"speciesKey": 2490494, "count": 2801754}, {"speciesKey": 2489590, "count": 2793437}, {"speciesKey": 2481800, "count": 2788284}, {"speciesKey": 2498257, "count": 2787634}, {"speciesKey": 5229167, "count": 2778252}, {"speciesKey": 6101224, "count": 2765549}, {"speciesKey": 2482598, "count": 2760153}, {"speciesKey": 2498352, "count": 2742907}, {"speciesKey": 2482755, "count": 2739555}, {"speciesKey": 2478605, "count": 2720512}, {"speciesKey": 5229487, "count": 2681583}, {"speciesKey": 2475532, "count": 2589965}, {"speciesKey": 1920506, "count": 2560274}, {"speciesKey": 8084280, "count": 2555759}, {"speciesKey": 2494988, "count": 2553524}, {"speciesKey": 2489214, "count": 2552837}, {"speciesKey": 2498009, "count": 2534006}, {"speciesKey": 2481236, "count": 2531950}, {"speciesKey": 2492606, "count": 2526134}, {"speciesKey": 2474950, "count": 2520285}, {"speciesKey": 2480327, "count": 2516776}, {"speciesKey": 2481792, "count": 2512759}, {"speciesKey": 2487871, "count": 2505517}, {"speciesKey": 2490821, "count": 2496966}, {"speciesKey": 2474953, "count": 2487224}, {"speciesKey": 2487413, "count": 2487157}, {"speciesKey": 5739315, "count": 2478888}, {"speciesKey": 2489160, "count": 2468069}, {"speciesKey": 1894840, "count": 2465680}, {"speciesKey": 2478523, "count": 2454551}, {"speciesKey": 2484254, "count": 2429881}, {"speciesKey": 4408759, "count": 2388433}, {"speciesKey": 9596413, "count": 2372056}, {"speciesKey": 2481819, "count": 2345923}, {"speciesKey": 2489169, "count": 2343045}, {"speciesKey": 9783587, "count": 2338213}, {"speciesKey": 7357320, "count": 2337601}, {"speciesKey": 5229205, "count": 2331626}, {"speciesKey": 5220126, "count": 2325379}, {"speciesKey": 2262087, "count": 2323618}, {"speciesKey": 5184461, "count": 2322431}, {"speciesKey": 2260584, "count": 2318486}, {"speciesKey": 2492943, "count": 2315548}, {"speciesKey": 11059991, "count": 2314251}, {"speciesKey": 11711225, "count": 2313291}, {"speciesKey": 2259417, "count": 2312940}, {"speciesKey": 2262473, "count": 2312903}, {"speciesKey": 2263005, "count": 2312552}, {"speciesKey": 2260018, "count": 2312524}, {"speciesKey": 5184878, "count": 2312511}, {"speciesKey": 5185297, "count": 2312511}, {"speciesKey": 5184444, "count": 2312370}, {"speciesKey": 2480894, "count": 2312108}, {"speciesKey": 5229662, "count": 2268962}, {"speciesKey": 2490872, "count": 2268281}, {"speciesKey": 1920712, "count": 2260696}, {"speciesKey": 7341606, "count": 2254701}, {"speciesKey": 5140214, "count": 2225286}, {"speciesKey": 2498252, "count": 2222920}, {"speciesKey": 2498347, "count": 2214289}, {"speciesKey": 2481776, "count": 2201006}, {"speciesKey": 2489129, "count": 2193713}, {"speciesKey": 2490781, "count": 2180725}, {"speciesKey": 2481721, "count": 2178275}, {"speciesKey": 2480964, "count": 2177972}, {"speciesKey": 5229155, "count": 2169211}, {"speciesKey": 2480449, "count": 2137511}, {"speciesKey": 2481748, "count": 2136291}, {"speciesKey": 6092631, "count": 2121118}, {"speciesKey": 2487783, "count": 2113462}, {"speciesKey": 2484183, "count": 2103994}, {"speciesKey": 2490310, "count": 2091356}, {"speciesKey": 2481726, "count": 2084031}, {"speciesKey": 9813242, "count": 2079688}, {"speciesKey": 2486655, "count": 2073556}, {"speciesKey": 5789298, "count": 2072874}, {"speciesKey": 9701857, "count": 2065584}, {"speciesKey": 9415596, "count": 2063634}, {"speciesKey": 2493863, "count": 2062604}, {"speciesKey": 4284072, "count": 2027989}, {"speciesKey": 5231918, "count": 2016212}, {"speciesKey": 5229168, "count": 1995539}, {"speciesKey": 7341600, "count": 1994407}, {"speciesKey": 6093209, "count": 1979419}, {"speciesKey": 2481912, "count": 1955781}, {"speciesKey": 6092942, "count": 1951448}, {"speciesKey": 7622059, "count": 1950655}, {"speciesKey": 2492192, "count": 1948486}, {"speciesKey": 9740253, "count": 1946525}, {"speciesKey": 2479226, "count": 1937607}, {"speciesKey": 2488485, "count": 1937299}, {"speciesKey": 2491872, "count": 1932582}, {"speciesKey": 7960979, "count": 1920532}, {"speciesKey": 5230789, "count": 1911339}, {"speciesKey": 2414014, "count": 1897519}, {"speciesKey": 2482059, "count": 1886542}, {"speciesKey": 5229128, "count": 1884035}, {"speciesKey": 2493129, "count": 1877671}, {"speciesKey": 2488517, "count": 1857334}, {"speciesKey": 2498255, "count": 1849150}, {"speciesKey": 7531611, "count": 1841726}, {"speciesKey": 2478133, "count": 1830724}, {"speciesKey": 8346347, "count": 1827557}, {"speciesKey": 2483607, "count": 1819095}, {"speciesKey": 7806848, "count": 1814892}, {"speciesKey": 2482513, "count": 1814025}, {"speciesKey": 9413670, "count": 1813863}, {"speciesKey": 5231722, "count": 1806283}, {"speciesKey": 9566659, "count": 1806002}, {"speciesKey": 5230754, "count": 1799547}, {"speciesKey": 5231138, "count": 1796408}, {"speciesKey": 5219243, "count": 1782749}, {"speciesKey": 2494200, "count": 1781592}, {"speciesKey": 2481146, "count": 1776168}, {"speciesKey": 5231240, "count": 1769519}, {"speciesKey": 2494441, "count": 1768357}, {"speciesKey": 1911461, "count": 1763566}, {"speciesKey": 2480295, "count": 1753985}, {"speciesKey": 2498017, "count": 1737064}, {"speciesKey": 2481784, "count": 1732121}, {"speciesKey": 5229247, "count": 1728242}, {"speciesKey": 2498263, "count": 1723433}, {"speciesKey": 2492942, "count": 1718923}, {"speciesKey": 1896841, "count": 1714047}, {"speciesKey": 2490774, "count": 1707832}, {"speciesKey": 5739317, "count": 1704865}, {"speciesKey": 2481728, "count": 1674961}, {"speciesKey": 2487456, "count": 1665005}, {"speciesKey": 2480881, "count": 1663913}, {"speciesKey": 2479686, "count": 1646993}, {"speciesKey": 5959118, "count": 1644807}, {"speciesKey": 9656686, "count": 1644693}, {"speciesKey": 2490936, "count": 1642693}, {"speciesKey": 2481342, "count": 1641925}, {"speciesKey": 2478130, "count": 1635027}, {"speciesKey": 2492870, "count": 1633786}, {"speciesKey": 8208358, "count": 1633636}, {"speciesKey": 2481817, "count": 1617456}, {"speciesKey": 7415507, "count": 1606947}, {"speciesKey": 2480389, "count": 1603735}, {"speciesKey": 2498273, "count": 1593884}, {"speciesKey": 2490246, "count": 1584965}, {"speciesKey": 2498265, "count": 1583930}, {"speciesKey": 2481713, "count": 1579608}, {"speciesKey": 2705308, "count": 1579509}, {"speciesKey": 2493012, "count": 1578426}, {"speciesKey": 3120060, "count": 1578109}, {"speciesKey": 2481196, "count": 1573918}, {"speciesKey": 5232464, "count": 1566746}, {"speciesKey": 2482082, "count": 1564552}, {"speciesKey": 2487516, "count": 1564273}, {"speciesKey": 1898544, "count": 1560093}, {"speciesKey": 2479598, "count": 1556803}, {"speciesKey": 2484133, "count": 1550585}, {"speciesKey": 5231103, "count": 1549387}, {"speciesKey": 8250742, "count": 1548857}, {"speciesKey": 5358748, "count": 1548086}, {"speciesKey": 2482487, "count": 1543962}, {"speciesKey": 2490487, "count": 1543443}, {"speciesKey": 9399113, "count": 1534573}, {"speciesKey": 9629160, "count": 1533311}, {"speciesKey": 2495471, "count": 1527734}, {"speciesKey": 5219858, "count": 1525090}, {"speciesKey": 2487843, "count": 1518768}, {"speciesKey": 6065818, "count": 1513136}, {"speciesKey": 2878688, "count": 1511841}, {"speciesKey": 5229126, "count": 1507237}, {"speciesKey": 2482499, "count": 1502647}, {"speciesKey": 6101223, "count": 1502178}, {"speciesKey": 2493970, "count": 1496433}, {"speciesKey": 5232446, "count": 1494049}, {"speciesKey": 5228080, "count": 1486587}, {"speciesKey": 5229675, "count": 1484793}, {"speciesKey": 2480773, "count": 1474027}, {"speciesKey": 5229134, "count": 1466370}, {"speciesKey": 2881550, "count": 1462428}, {"speciesKey": 2488602, "count": 1460407}, {"speciesKey": 2482065, "count": 1457292}, {"speciesKey": 2359706, "count": 1456400}, {"speciesKey": 3172358, "count": 1453217}, {"speciesKey": 2498167, "count": 1451686}, {"speciesKey": 2490804, "count": 1449751}, {"speciesKey": 2481958, "count": 1449271}, {"speciesKey": 2488484, "count": 1445767}, {"speciesKey": 5422328, "count": 1445359}, {"speciesKey": 6093856, "count": 1442706}, {"speciesKey": 5229935, "count": 1440022}, {"speciesKey": 2482791, "count": 1437037}, {"speciesKey": 2487825, "count": 1430093}, {"speciesKey": 2486131, "count": 1427697}, {"speciesKey": 2480989, "count": 1426135}, {"speciesKey": 2487144, "count": 1419152}, {"speciesKey": 5789281, "count": 1417056}, {"speciesKey": 2882316, "count": 1416487}, {"speciesKey": 4299368, "count": 1409610}, {"speciesKey": 7595433, "count": 1405874}, {"speciesKey": 1919712, "count": 1405413}, {"speciesKey": 8324121, "count": 1398111}, {"speciesKey": 2487365, "count": 1394218}, {"speciesKey": 2494329, "count": 1388973}, {"speciesKey": 3033339, "count": 1386604}, {"speciesKey": 2498084, "count": 1382709}, {"speciesKey": 2498246, "count": 1375218}, {"speciesKey": 2415631, "count": 1368089}, {"speciesKey": 2492960, "count": 1368000}, {"speciesKey": 5228328, "count": 1362482}, {"speciesKey": 3113414, "count": 1362027}, {"speciesKey": 2481433, "count": 1351759}, {"speciesKey": 2489396, "count": 1346400}, {"speciesKey": 9283578, "count": 1344502}, {"speciesKey": 2492576, "count": 1342220}, {"speciesKey": 2706164, "count": 1341881}, {"speciesKey": 1789695, "count": 1339337}, {"speciesKey": 2496287, "count": 1339110}, {"speciesKey": 5229754, "count": 1337866}, {"speciesKey": 2487866, "count": 1331450}, {"speciesKey": 2475648, "count": 1330775}, {"speciesKey": 2479888, "count": 1328497}, {"speciesKey": 2497541, "count": 1310602}, {"speciesKey": 2490263, "count": 1307947}, {"speciesKey": 2487883, "count": 1303412}, {"speciesKey": 2480801, "count": 1301615}, {"speciesKey": 2480524, "count": 1294416}, {"speciesKey": 2481685, "count": 1286161}, {"speciesKey": 2498415, "count": 1285690}, {"speciesKey": 2493744, "count": 1278884}, {"speciesKey": 2481240, "count": 1277716}, {"speciesKey": 5230862, "count": 1276972}, {"speciesKey": 2487453, "count": 1269525}, {"speciesKey": 7745240, "count": 1264195}, {"speciesKey": 2480259, "count": 1248206}, {"speciesKey": 1929697, "count": 1245261}, {"speciesKey": 6093199, "count": 1243540}, {"speciesKey": 5229146, "count": 1237175}, {"speciesKey": 2481764, "count": 1235238}, {"speciesKey": 6065811, "count": 1232112}, {"speciesKey": 2875979, "count": 1229641}, {"speciesKey": 2495190, "count": 1227772}, {"speciesKey": 9088491, "count": 1216086}, {"speciesKey": 7340825, "count": 1212443}, {"speciesKey": 2480538, "count": 1211252}, {"speciesKey": 2477872, "count": 1206651}, {"speciesKey": 7660710, "count": 1202941}, {"speciesKey": 2882482, "count": 1202422}, {"speciesKey": 5290149, "count": 1202201}, {"speciesKey": 2482913, "count": 1200527}, {"speciesKey": 2496347, "count": 1193171}, {"speciesKey": 2487603, "count": 1190394}, {"speciesKey": 8959883, "count": 1189582}, {"speciesKey": 7341828, "count": 1188095}, {"speciesKey": 2987999, "count": 1187272}, {"speciesKey": 1341976, "count": 1185582}, {"speciesKey": 2492680, "count": 1183832}, {"speciesKey": 9345027, "count": 1177734}, {"speciesKey": 2888951, "count": 1175398}, {"speciesKey": 2483647, "count": 1173354}, {"speciesKey": 2482051, "count": 1172036}, {"speciesKey": 2493028, "count": 1168276}, {"speciesKey": 2484605, "count": 1167836}, {"speciesKey": 2492822, "count": 1165287}, {"speciesKey": 3033363, "count": 1161475}, {"speciesKey": 2481710, "count": 1161397}, {"speciesKey": 2498393, "count": 1156403}, {"speciesKey": 2495858, "count": 1154470}, {"speciesKey": 9220780, "count": 1147153}, {"speciesKey": 2926557, "count": 1145503}, {"speciesKey": 2481205, "count": 1140243}, {"speciesKey": 7634625, "count": 1139301}, {"speciesKey": 7705930, "count": 1134846}, {"speciesKey": 2496060, "count": 1134134}, {"speciesKey": 2490716, "count": 1133223}, {"speciesKey": 2480258, "count": 1129756}, {"speciesKey": 2498256, "count": 1125458}, {"speciesKey": 3012167, "count": 1119478}, {"speciesKey": 2482524, "count": 1114927}, {"speciesKey": 2701311, "count": 1107207}, {"speciesKey": 5285637, "count": 1105294}, {"speciesKey": 5212973, "count": 1105189}, {"speciesKey": 3189870, "count": 1102422}, {"speciesKey": 2434814, "count": 1100267}, {"speciesKey": 2495266, "count": 1098584}, {"speciesKey": 2489448, "count": 1095544}, {"speciesKey": 2482357, "count": 1093875}, {"speciesKey": 2704922, "count": 1092272}, {"speciesKey": 7389824, "count": 1091729}, {"speciesKey": 3189767, "count": 1089783}, {"speciesKey": 2487905, "count": 1089557}, {"speciesKey": 2498338, "count": 1086019}, {"speciesKey": 2489104, "count": 1085296}, {"speciesKey": 2706490, "count": 1085133}, {"speciesKey": 2482033, "count": 1084211}, {"speciesKey": 2484904, "count": 1082734}, {"speciesKey": 4409653, "count": 1080497}, {"speciesKey": 6092935, "count": 1079580}, {"speciesKey": 2492521, "count": 1079087}, {"speciesKey": 5228513, "count": 1078869}, {"speciesKey": 2480897, "count": 1077863}, {"speciesKey": 2480332, "count": 1077393}, {"speciesKey": 9568685, "count": 1075094}, {"speciesKey": 7952072, "count": 1071758}, {"speciesKey": 2487397, "count": 1070285}, {"speciesKey": 4408732, "count": 1069666}, {"speciesKey": 5357013, "count": 1069156}]}